CHANGELOG.txt
LICENCE.txt
MANIFEST.in
README.txt
setup.py
naitancalculator/__init__.py
naitancalculator.egg-info/PKG-INFO
naitancalculator.egg-info/SOURCES.txt
naitancalculator.egg-info/dependency_links.txt
naitancalculator.egg-info/top_level.txt