Metadata-Version: 1.1
Name: naitancalculator
Version: 0.1
Summary: A very basic calculator
Home-page: UNKNOWN
Author: Aditya Naitan
Author-email: adityanaitan@gmail.com
License: MIT
Keywords: calculator,naitancalculator,add,substract,multiply,divide
Platform: UNKNOWN
Classifier: Development Status :: 5 - Production/Stable
Classifier: Intended Audience :: Education
Classifier: Operating System :: Microsoft :: Windows :: Windows 10
Classifier: License :: OSI Approved :: MIT License
Classifier: Programming Language :: Python :: 3
Classifier: Programming Language :: Python :: 3.4
Classifier: Programming Language :: Python :: 3.5
Classifier: Programming Language :: Python :: 3.6
Classifier: Programming Language :: Python :: 3.7
